django_access_inspector/__init__.py
django_access_inspector/apps.py
django_access_inspector/mcp_server.py
django_access_inspector/models.py
django_access_inspector/permissions.py
django_access_inspector/settings.py
django_access_inspector/urls.py
django_access_inspector/views.py
django_access_inspector/management/commands/__init__.py
django_access_inspector/management/commands/inspect_access_control.py
django_access_inspector/management/commands/start_mcp_server.py
django_access_inspector/migrations/__init__.py
django_access_inspector/services/__init__.py
django_access_inspector/services/debug_logger.py
django_access_inspector/services/models.py
django_access_inspector/services/report_generator.py
django_access_inspector/services/snapshot.py
django_access_inspector/services/url_analyzer.py
django_access_inspector/services/view_inspector.py
django_access_inspector/tests/__init__.py
django_access_inspector/tests/test_ci_integration.py
django_access_inspector/tests/test_command_ci_mode.py
django_access_inspector/tests/test_models.py
django_access_inspector/tests/test_report_generator_ci.py
django_access_inspector/tests/test_report_generator_service.py
django_access_inspector/tests/test_snapshot_service.py
django_access_inspector/tests/test_url_analyzer_service.py
django_access_inspector/tests/test_view_inspector_service.py
django_access_inspector/tests/management/commands/__init__.py
django_access_inspector/tests/management/commands/snapshot.json
django_access_inspector/tests/management/commands/test_inspect_access_control.py
django_access_inspector/tests/mocks/permissions.py
django_access_inspector/tests/mocks/views.py
django_access_inspector-0.4.2.dist-info/METADATA
django_access_inspector-0.4.2.dist-info/WHEEL
django_access_inspector-0.4.2.dist-info/RECORD
