Metadata-Version: 2.3
Name: django-access-inspector
Version: 0.4.2
Summary: A tool to analyze your Django app access control
Project-URL: Repository, https://github.com/BastienTeissier/django-access-inspector
Author-email: Bastien Teissier <bastient@theodo.fr>
License: MIT License
Requires-Python: ~=3.10
Requires-Dist: fastmcp<2.15,>=2.14.2
Requires-Dist: pydantic<3,>=2.12
Requires-Dist: rich<14,>=13.3.5
Requires-Dist: twine<6,>=5.1.1
